rdflib_gs1/__init__.py
rdflib_gs1/namespace/_GS1.py
rdflib_gs1/namespace/__init__.py
rdflib_gs1-0.1.2.dist-info/METADATA
rdflib_gs1-0.1.2.dist-info/WHEEL
rdflib_gs1-0.1.2.dist-info/entry_points.txt
rdflib_gs1-0.1.2.dist-info/RECORD
