Metadata-Version: 2.1
Name: rdflib-gs1
Version: 0.1.2
Summary: The GS1 Web Vocabulary as an rdflib namespace.
Author: David Riccitelli
Author-email: david@wordlift.io
Requires-Python: >=3.10,<3.13
Classifier: Programming Language :: Python :: 3
Classifier: Programming Language :: Python :: 3.10
Classifier: Programming Language :: Python :: 3.11
Classifier: Programming Language :: Python :: 3.12
Requires-Dist: rdflib (>=7.1.0,<8.0.0)
